github_downloader/__init__.py
github_downloader/cli.py
github_downloader/downloader.py
github_folder_downloader-0.1.1.dist-info/METADATA
github_folder_downloader-0.1.1.dist-info/WHEEL
github_folder_downloader-0.1.1.dist-info/entry_points.txt
github_folder_downloader-0.1.1.dist-info/top_level.txt
github_folder_downloader-0.1.1.dist-info/RECORD
