Metadata-Version: 2.1
Name: github-folder-downloader
Version: 0.1.1
Summary: A tool to download files and folders from GitHub repositories
Home-page: https://github.com/soykot2910/github-folder-downloader
Author: Md.Soykot
Author-email: md.soykot2910@gmail.com
Classifier: Programming Language :: Python :: 3
Classifier: License :: OSI Approved :: MIT License
Classifier: Operating System :: OS Independent
Requires-Python: >=3.6
Requires-Dist: requests >=2.25.0
